json2mdheadings/__init__.py
json2mdheadings/json2mdheadings.py
tests/__init__.py
tests/test_json2mdheadings.py
json2mdheadings-0.1.0.dist-info/LICENSE
json2mdheadings-0.1.0.dist-info/METADATA
json2mdheadings-0.1.0.dist-info/WHEEL
json2mdheadings-0.1.0.dist-info/top_level.txt
json2mdheadings-0.1.0.dist-info/RECORD
